augfeat/autoencoder.py
augfeat/balancer.py
augfeat/config.py
augfeat/custom_data_type_interface.py
augfeat/custom_types.py
augfeat-1.0.0.dist-info/LICENSE
augfeat-1.0.0.dist-info/METADATA
augfeat-1.0.0.dist-info/WHEEL
augfeat-1.0.0.dist-info/top_level.txt
augfeat-1.0.0.dist-info/RECORD
