Metadata-Version: 2.1
Name: augfeat
Version: 1.0.0
Summary: Data augmentation in features space
Author-email: Hubert <hubert.hamelin@gmail.com>
License: The MIT License (MIT)
Project-URL: Homepage, https://github.com/HubertHamelin/augfeat
Keywords: augmentation,data,machine-learning
Classifier: License :: OSI Approved :: MIT License
Classifier: Programming Language :: Python
Classifier: Programming Language :: Python :: 3
Requires-Python: >=3.9
License-File: LICENSE
Requires-Dist: numpy
Requires-Dist: scikit-learn
Requires-Dist: tqdm
Requires-Dist: matplotlib
Requires-Dist: keras
Requires-Dist: pandas
Requires-Dist: Pillow
Requires-Dist: idx2numpy
